nourish/__init__.py
nourish/_config.py
nourish/_dataset.py
nourish/_extractors.py
nourish/_high_level.py
nourish/_lock.py
nourish/_schema.py
nourish/_schema_retrieval.py
nourish/_typing.py
nourish/_version.py
nourish/dataset.py
nourish/exceptions.py
nourish/schema.py
nourish/typing.py
nourish/loaders/__init__.py
nourish/loaders/_base.py
nourish/loaders/_format_loader_map.py
nourish/loaders/_table.py
nourish/loaders/_text.py
nourish/loaders/table.py
nourish/loaders/text.py
nourish-0.1a2.data/data/LICENSE
nourish-0.1a2.dist-info/AUTHORS.rst
nourish-0.1a2.dist-info/LICENSE
nourish-0.1a2.dist-info/METADATA
nourish-0.1a2.dist-info/WHEEL
nourish-0.1a2.dist-info/top_level.txt
nourish-0.1a2.dist-info/RECORD
